simple_accounting/__init__.py
simple_accounting/admin.py
simple_accounting/migrations/0001_initial.py
simple_accounting/migrations/__init__.py
simple_accounting/models.py
simple_accounting/utils.py
django_simple_accounting-0.1.4.dist-info/LICENSE
django_simple_accounting-0.1.4.dist-info/METADATA
django_simple_accounting-0.1.4.dist-info/WHEEL
django_simple_accounting-0.1.4.dist-info/RECORD
