Metadata-Version: 2.1
Name: django-simple-accounting
Version: 0.1.4
Summary: Plain and simple accounting module for Django
License: MIT
Author: Šarūnas Navickas
Author-email: sarunas@griaustinis.lt
Requires-Python: >=3.9,<4.0
Classifier: License :: OSI Approved :: MIT License
Classifier: Programming Language :: Python :: 3
Classifier: Programming Language :: Python :: 3.9
Classifier: Programming Language :: Python :: 3.10
Classifier: Programming Language :: Python :: 3.11
Requires-Dist: pydantic (>=1.10.9,<2.0.0)
